[{"Quartiere":1,"Fascia":"65..","UominiStranieri":46,"UominiTicinesi":18,"UominiConfederati":59,"UominiAttinenti":22,"DonneAttinenti":30,"DonneConfederate":42,"DonneTicinesi":14,"DonneStraniere":23},{"Quartiere":1,"Fascia":"20..64","UominiStranieri":88,"UominiTicinesi":28,"UominiConfederati":41,"UominiAttinenti":51,"DonneAttinenti":46,"DonneConfederate":40,"DonneTicinesi":27,"DonneStraniere":63},{"Quartiere":1,"Fascia":"0..19","UominiStranieri":5,"UominiTicinesi":6,"UominiConfederati":6,"UominiAttinenti":13,"DonneAttinenti":12,"DonneConfederate":6,"DonneTicinesi":3,"DonneStraniere":8},{"Quartiere":2,"Fascia":"65..","UominiStranieri":147,"UominiTicinesi":122,"UominiConfederati":84,"UominiAttinenti":79,"DonneAttinenti":148,"DonneConfederate":190,"DonneTicinesi":234,"DonneStraniere":172},{"Quartiere":2,"Fascia":"20..64","UominiStranieri":867,"UominiTicinesi":281,"UominiConfederati":189,"UominiAttinenti":222,"DonneAttinenti":246,"DonneConfederate":218,"DonneTicinesi":364,"DonneStraniere":766},{"Quartiere":2,"Fascia":"0..19","UominiStranieri":152,"UominiTicinesi":83,"UominiConfederati":57,"UominiAttinenti":82,"DonneAttinenti":72,"DonneConfederate":63,"DonneTicinesi":102,"DonneStraniere":133},{"Quartiere":3,"Fascia":"65..","UominiStranieri":6,"UominiTicinesi":5,"UominiConfederati":20,"UominiAttinenti":11,"DonneAttinenti":23,"DonneConfederate":13,"DonneTicinesi":4,"DonneStraniere":0},{"Quartiere":3,"Fascia":"20..64","UominiStranieri":22,"UominiTicinesi":26,"UominiConfederati":29,"UominiAttinenti":46,"DonneAttinenti":50,"DonneConfederate":21,"DonneTicinesi":26,"DonneStraniere":24},{"Quartiere":3,"Fascia":"0..19","UominiStranieri":5,"UominiTicinesi":8,"UominiConfederati":7,"UominiAttinenti":15,"DonneAttinenti":10,"DonneConfederate":6,"DonneTicinesi":6,"DonneStraniere":6},{"Quartiere":4,"Fascia":"65..","UominiStranieri":130,"UominiTicinesi":130,"UominiConfederati":120,"UominiAttinenti":114,"DonneAttinenti":152,"DonneConfederate":165,"DonneTicinesi":216,"DonneStraniere":131},{"Quartiere":4,"Fascia":"20..64","UominiStranieri":534,"UominiTicinesi":438,"UominiConfederati":258,"UominiAttinenti":330,"DonneAttinenti":381,"DonneConfederate":317,"DonneTicinesi":473,"DonneStraniere":504},{"Quartiere":4,"Fascia":"0..19","UominiStranieri":132,"UominiTicinesi":153,"UominiConfederati":122,"UominiAttinenti":128,"DonneAttinenti":134,"DonneConfederate":118,"DonneTicinesi":156,"DonneStraniere":111},{"Quartiere":5,"Fascia":"65..","UominiStranieri":186,"UominiTicinesi":74,"UominiConfederati":52,"UominiAttinenti":85,"DonneAttinenti":158,"DonneConfederate":141,"DonneTicinesi":140,"DonneStraniere":211},{"Quartiere":5,"Fascia":"20..64","UominiStranieri":635,"UominiTicinesi":152,"UominiConfederati":101,"UominiAttinenti":204,"DonneAttinenti":215,"DonneConfederate":139,"DonneTicinesi":145,"DonneStraniere":559},{"Quartiere":5,"Fascia":"0..19","UominiStranieri":94,"UominiTicinesi":50,"UominiConfederati":32,"UominiAttinenti":67,"DonneAttinenti":71,"DonneConfederate":25,"DonneTicinesi":39,"DonneStraniere":102},{"Quartiere":6,"Fascia":"65..","UominiStranieri":168,"UominiTicinesi":39,"UominiConfederati":91,"UominiAttinenti":70,"DonneAttinenti":92,"DonneConfederate":104,"DonneTicinesi":64,"DonneStraniere":139},{"Quartiere":6,"Fascia":"20..64","UominiStranieri":389,"UominiTicinesi":112,"UominiConfederati":113,"UominiAttinenti":111,"DonneAttinenti":118,"DonneConfederate":99,"DonneTicinesi":118,"DonneStraniere":330},{"Quartiere":6,"Fascia":"0..19","UominiStranieri":83,"UominiTicinesi":40,"UominiConfederati":18,"UominiAttinenti":43,"DonneAttinenti":35,"DonneConfederate":17,"DonneTicinesi":46,"DonneStraniere":76},{"Quartiere":7,"Fascia":"65..","UominiStranieri":227,"UominiTicinesi":140,"UominiConfederati":80,"UominiAttinenti":113,"DonneAttinenti":211,"DonneConfederate":162,"DonneTicinesi":234,"DonneStraniere":262},{"Quartiere":7,"Fascia":"20..64","UominiStranieri":959,"UominiTicinesi":260,"UominiConfederati":187,"UominiAttinenti":248,"DonneAttinenti":285,"DonneConfederate":196,"DonneTicinesi":331,"DonneStraniere":851},{"Quartiere":7,"Fascia":"0..19","UominiStranieri":143,"UominiTicinesi":80,"UominiConfederati":61,"UominiAttinenti":96,"DonneAttinenti":76,"DonneConfederate":49,"DonneTicinesi":96,"DonneStraniere":160},{"Quartiere":8,"Fascia":"65..","UominiStranieri":4,"UominiTicinesi":4,"UominiConfederati":4,"UominiAttinenti":2,"DonneAttinenti":4,"DonneConfederate":5,"DonneTicinesi":3,"DonneStraniere":1},{"Quartiere":8,"Fascia":"20..64","UominiStranieri":16,"UominiTicinesi":11,"UominiConfederati":7,"UominiAttinenti":16,"DonneAttinenti":21,"DonneConfederate":9,"DonneTicinesi":13,"DonneStraniere":13},{"Quartiere":8,"Fascia":"0..19","UominiStranieri":4,"UominiTicinesi":4,"UominiConfederati":3,"UominiAttinenti":11,"DonneAttinenti":5,"DonneConfederate":3,"DonneTicinesi":4,"DonneStraniere":6},{"Quartiere":9,"Fascia":"65..","UominiStranieri":23,"UominiTicinesi":37,"UominiConfederati":16,"UominiAttinenti":63,"DonneAttinenti":63,"DonneConfederate":21,"DonneTicinesi":50,"DonneStraniere":18},{"Quartiere":9,"Fascia":"20..64","UominiStranieri":97,"UominiTicinesi":149,"UominiConfederati":100,"UominiAttinenti":160,"DonneAttinenti":192,"DonneConfederate":102,"DonneTicinesi":155,"DonneStraniere":79},{"Quartiere":9,"Fascia":"0..19","UominiStranieri":24,"UominiTicinesi":61,"UominiConfederati":34,"UominiAttinenti":68,"DonneAttinenti":46,"DonneConfederate":43,"DonneTicinesi":50,"DonneStraniere":26},{"Quartiere":10,"Fascia":"65..","UominiStranieri":7,"UominiTicinesi":4,"UominiConfederati":12,"UominiAttinenti":6,"DonneAttinenti":6,"DonneConfederate":16,"DonneTicinesi":7,"DonneStraniere":6},{"Quartiere":10,"Fascia":"20..64","UominiStranieri":17,"UominiTicinesi":23,"UominiConfederati":22,"UominiAttinenti":29,"DonneAttinenti":24,"DonneConfederate":19,"DonneTicinesi":19,"DonneStraniere":20},{"Quartiere":10,"Fascia":"0..19","UominiStranieri":0,"UominiTicinesi":7,"UominiConfederati":4,"UominiAttinenti":10,"DonneAttinenti":8,"DonneConfederate":4,"DonneTicinesi":4,"DonneStraniere":2},{"Quartiere":11,"Fascia":"65..","UominiStranieri":177,"UominiTicinesi":57,"UominiConfederati":69,"UominiAttinenti":50,"DonneAttinenti":98,"DonneConfederate":116,"DonneTicinesi":112,"DonneStraniere":189},{"Quartiere":11,"Fascia":"20..64","UominiStranieri":715,"UominiTicinesi":108,"UominiConfederati":82,"UominiAttinenti":125,"DonneAttinenti":127,"DonneConfederate":113,"DonneTicinesi":113,"DonneStraniere":622},{"Quartiere":11,"Fascia":"0..19","UominiStranieri":122,"UominiTicinesi":35,"UominiConfederati":25,"UominiAttinenti":53,"DonneAttinenti":47,"DonneConfederate":21,"DonneTicinesi":25,"DonneStraniere":116},{"Quartiere":12,"Fascia":"65..","UominiStranieri":321,"UominiTicinesi":180,"UominiConfederati":108,"UominiAttinenti":224,"DonneAttinenti":416,"DonneConfederate":217,"DonneTicinesi":382,"DonneStraniere":399},{"Quartiere":12,"Fascia":"20..64","UominiStranieri":1591,"UominiTicinesi":430,"UominiConfederati":255,"UominiAttinenti":502,"DonneAttinenti":594,"DonneConfederate":306,"DonneTicinesi":464,"DonneStraniere":1450},{"Quartiere":12,"Fascia":"0..19","UominiStranieri":315,"UominiTicinesi":125,"UominiConfederati":68,"UominiAttinenti":198,"DonneAttinenti":183,"DonneConfederate":73,"DonneTicinesi":127,"DonneStraniere":306},{"Quartiere":13,"Fascia":"65..","UominiStranieri":20,"UominiTicinesi":18,"UominiConfederati":8,"UominiAttinenti":12,"DonneAttinenti":21,"DonneConfederate":8,"DonneTicinesi":19,"DonneStraniere":16},{"Quartiere":13,"Fascia":"20..64","UominiStranieri":108,"UominiTicinesi":68,"UominiConfederati":29,"UominiAttinenti":50,"DonneAttinenti":56,"DonneConfederate":34,"DonneTicinesi":50,"DonneStraniere":79},{"Quartiere":13,"Fascia":"0..19","UominiStranieri":10,"UominiTicinesi":18,"UominiConfederati":15,"UominiAttinenti":17,"DonneAttinenti":22,"DonneConfederate":11,"DonneTicinesi":24,"DonneStraniere":16},{"Quartiere":14,"Fascia":"65..","UominiStranieri":53,"UominiTicinesi":33,"UominiConfederati":27,"UominiAttinenti":19,"DonneAttinenti":20,"DonneConfederate":29,"DonneTicinesi":35,"DonneStraniere":38},{"Quartiere":14,"Fascia":"20..64","UominiStranieri":276,"UominiTicinesi":101,"UominiConfederati":72,"UominiAttinenti":75,"DonneAttinenti":91,"DonneConfederate":71,"DonneTicinesi":100,"DonneStraniere":308},{"Quartiere":14,"Fascia":"0..19","UominiStranieri":35,"UominiTicinesi":44,"UominiConfederati":18,"UominiAttinenti":30,"DonneAttinenti":34,"DonneConfederate":19,"DonneTicinesi":45,"DonneStraniere":51},{"Quartiere":15,"Fascia":"65..","UominiStranieri":243,"UominiTicinesi":172,"UominiConfederati":144,"UominiAttinenti":200,"DonneAttinenti":266,"DonneConfederate":194,"DonneTicinesi":220,"DonneStraniere":235},{"Quartiere":15,"Fascia":"20..64","UominiStranieri":1220,"UominiTicinesi":544,"UominiConfederati":355,"UominiAttinenti":706,"DonneAttinenti":796,"DonneConfederate":473,"DonneTicinesi":602,"DonneStraniere":1150},{"Quartiere":15,"Fascia":"0..19","UominiStranieri":352,"UominiTicinesi":202,"UominiConfederati":140,"UominiAttinenti":289,"DonneAttinenti":256,"DonneConfederate":154,"DonneTicinesi":164,"DonneStraniere":275},{"Quartiere":16,"Fascia":"65..","UominiStranieri":227,"UominiTicinesi":164,"UominiConfederati":157,"UominiAttinenti":194,"DonneAttinenti":314,"DonneConfederate":243,"DonneTicinesi":295,"DonneStraniere":265},{"Quartiere":16,"Fascia":"20..64","UominiStranieri":1035,"UominiTicinesi":365,"UominiConfederati":268,"UominiAttinenti":461,"DonneAttinenti":583,"DonneConfederate":332,"DonneTicinesi":416,"DonneStraniere":951},{"Quartiere":16,"Fascia":"0..19","UominiStranieri":256,"UominiTicinesi":126,"UominiConfederati":100,"UominiAttinenti":169,"DonneAttinenti":166,"DonneConfederate":88,"DonneTicinesi":107,"DonneStraniere":223},{"Quartiere":17,"Fascia":"65..","UominiStranieri":62,"UominiTicinesi":32,"UominiConfederati":45,"UominiAttinenti":31,"DonneAttinenti":32,"DonneConfederate":60,"DonneTicinesi":34,"DonneStraniere":52},{"Quartiere":17,"Fascia":"20..64","UominiStranieri":237,"UominiTicinesi":174,"UominiConfederati":146,"UominiAttinenti":103,"DonneAttinenti":119,"DonneConfederate":140,"DonneTicinesi":184,"DonneStraniere":219},{"Quartiere":17,"Fascia":"0..19","UominiStranieri":68,"UominiTicinesi":72,"UominiConfederati":52,"UominiAttinenti":59,"DonneAttinenti":47,"DonneConfederate":49,"DonneTicinesi":75,"DonneStraniere":59},{"Quartiere":18,"Fascia":"65..","UominiStranieri":13,"UominiTicinesi":10,"UominiConfederati":21,"UominiAttinenti":13,"DonneAttinenti":21,"DonneConfederate":16,"DonneTicinesi":20,"DonneStraniere":10},{"Quartiere":18,"Fascia":"20..64","UominiStranieri":33,"UominiTicinesi":80,"UominiConfederati":37,"UominiAttinenti":46,"DonneAttinenti":50,"DonneConfederate":33,"DonneTicinesi":74,"DonneStraniere":31},{"Quartiere":18,"Fascia":"0..19","UominiStranieri":8,"UominiTicinesi":22,"UominiConfederati":16,"UominiAttinenti":17,"DonneAttinenti":15,"DonneConfederate":12,"DonneTicinesi":25,"DonneStraniere":4},{"Quartiere":19,"Fascia":"65..","UominiStranieri":4,"UominiTicinesi":9,"UominiConfederati":11,"UominiAttinenti":31,"DonneAttinenti":38,"DonneConfederate":11,"DonneTicinesi":12,"DonneStraniere":2},{"Quartiere":19,"Fascia":"20..64","UominiStranieri":26,"UominiTicinesi":49,"UominiConfederati":28,"UominiAttinenti":63,"DonneAttinenti":77,"DonneConfederate":30,"DonneTicinesi":48,"DonneStraniere":17},{"Quartiere":19,"Fascia":"0..19","UominiStranieri":4,"UominiTicinesi":18,"UominiConfederati":10,"UominiAttinenti":25,"DonneAttinenti":24,"DonneConfederate":9,"DonneTicinesi":28,"DonneStraniere":4},{"Quartiere":20,"Fascia":"65..","UominiStranieri":2,"UominiTicinesi":4,"UominiConfederati":3,"UominiAttinenti":6,"DonneAttinenti":10,"DonneConfederate":3,"DonneTicinesi":6,"DonneStraniere":2},{"Quartiere":20,"Fascia":"20..64","UominiStranieri":13,"UominiTicinesi":16,"UominiConfederati":8,"UominiAttinenti":16,"DonneAttinenti":11,"DonneConfederate":9,"DonneTicinesi":7,"DonneStraniere":11},{"Quartiere":20,"Fascia":"0..19","UominiStranieri":2,"UominiTicinesi":6,"UominiConfederati":4,"UominiAttinenti":9,"DonneAttinenti":4,"DonneConfederate":2,"DonneTicinesi":2,"DonneStraniere":2},{"Quartiere":21,"Fascia":"65..","UominiStranieri":34,"UominiTicinesi":42,"UominiConfederati":22,"UominiAttinenti":81,"DonneAttinenti":109,"DonneConfederate":34,"DonneTicinesi":49,"DonneStraniere":30},{"Quartiere":21,"Fascia":"20..64","UominiStranieri":158,"UominiTicinesi":190,"UominiConfederati":123,"UominiAttinenti":210,"DonneAttinenti":231,"DonneConfederate":154,"DonneTicinesi":201,"DonneStraniere":139},{"Quartiere":21,"Fascia":"0..19","UominiStranieri":46,"UominiTicinesi":71,"UominiConfederati":36,"UominiAttinenti":89,"DonneAttinenti":67,"DonneConfederate":33,"DonneTicinesi":64,"DonneStraniere":40},{"Quartiere":22,"Fascia":"65..","UominiStranieri":25,"UominiTicinesi":18,"UominiConfederati":23,"UominiAttinenti":11,"DonneAttinenti":20,"DonneConfederate":36,"DonneTicinesi":21,"DonneStraniere":19},{"Quartiere":22,"Fascia":"20..64","UominiStranieri":62,"UominiTicinesi":76,"UominiConfederati":75,"UominiAttinenti":46,"DonneAttinenti":49,"DonneConfederate":83,"DonneTicinesi":90,"DonneStraniere":61},{"Quartiere":22,"Fascia":"0..19","UominiStranieri":19,"UominiTicinesi":24,"UominiConfederati":23,"UominiAttinenti":11,"DonneAttinenti":18,"DonneConfederate":24,"DonneTicinesi":24,"DonneStraniere":19},{"Quartiere":23,"Fascia":"65..","UominiStranieri":2,"UominiTicinesi":1,"UominiConfederati":2,"UominiAttinenti":2,"DonneAttinenti":7,"DonneConfederate":2,"DonneTicinesi":0,"DonneStraniere":1},{"Quartiere":23,"Fascia":"20..64","UominiStranieri":4,"UominiTicinesi":9,"UominiConfederati":2,"UominiAttinenti":1,"DonneAttinenti":4,"DonneConfederate":2,"DonneTicinesi":7,"DonneStraniere":3},{"Quartiere":23,"Fascia":"0..19","UominiStranieri":0,"UominiTicinesi":3,"UominiConfederati":0,"UominiAttinenti":0,"DonneAttinenti":1,"DonneConfederate":0,"DonneTicinesi":2,"DonneStraniere":0},{"Quartiere":24,"Fascia":"65..","UominiStranieri":1,"UominiTicinesi":1,"UominiConfederati":3,"UominiAttinenti":11,"DonneAttinenti":9,"DonneConfederate":1,"DonneTicinesi":0,"DonneStraniere":0},{"Quartiere":24,"Fascia":"20..64","UominiStranieri":3,"UominiTicinesi":13,"UominiConfederati":11,"UominiAttinenti":13,"DonneAttinenti":21,"DonneConfederate":7,"DonneTicinesi":11,"DonneStraniere":3},{"Quartiere":24,"Fascia":"0..19","UominiStranieri":1,"UominiTicinesi":3,"UominiConfederati":4,"UominiAttinenti":3,"DonneAttinenti":3,"DonneConfederate":0,"DonneTicinesi":1,"DonneStraniere":0},{"Quartiere":25,"Fascia":"65..","UominiStranieri":22,"UominiTicinesi":43,"UominiConfederati":28,"UominiAttinenti":92,"DonneAttinenti":129,"DonneConfederate":37,"DonneTicinesi":41,"DonneStraniere":7},{"Quartiere":25,"Fascia":"20..64","UominiStranieri":91,"UominiTicinesi":167,"UominiConfederati":78,"UominiAttinenti":225,"DonneAttinenti":248,"DonneConfederate":89,"DonneTicinesi":165,"DonneStraniere":75},{"Quartiere":25,"Fascia":"0..19","UominiStranieri":19,"UominiTicinesi":65,"UominiConfederati":38,"UominiAttinenti":73,"DonneAttinenti":77,"DonneConfederate":29,"DonneTicinesi":67,"DonneStraniere":9},{"Quartiere":26,"Fascia":"65..","UominiStranieri":7,"UominiTicinesi":15,"UominiConfederati":8,"UominiAttinenti":45,"DonneAttinenti":58,"DonneConfederate":12,"DonneTicinesi":32,"DonneStraniere":2},{"Quartiere":26,"Fascia":"20..64","UominiStranieri":26,"UominiTicinesi":54,"UominiConfederati":27,"UominiAttinenti":96,"DonneAttinenti":82,"DonneConfederate":41,"DonneTicinesi":59,"DonneStraniere":23},{"Quartiere":26,"Fascia":"0..19","UominiStranieri":0,"UominiTicinesi":26,"UominiConfederati":10,"UominiAttinenti":18,"DonneAttinenti":28,"DonneConfederate":11,"DonneTicinesi":20,"DonneStraniere":4},{"Quartiere":106,"Fascia":"65..","UominiStranieri":5,"UominiTicinesi":2,"UominiConfederati":7,"UominiAttinenti":0,"DonneAttinenti":1,"DonneConfederate":4,"DonneTicinesi":1,"DonneStraniere":8},{"Quartiere":106,"Fascia":"20..64","UominiStranieri":4,"UominiTicinesi":2,"UominiConfederati":11,"UominiAttinenti":1,"DonneAttinenti":0,"DonneConfederate":12,"DonneTicinesi":4,"DonneStraniere":3},{"Quartiere":106,"Fascia":"0..19","UominiStranieri":2,"UominiTicinesi":0,"UominiConfederati":3,"UominiAttinenti":0,"DonneAttinenti":0,"DonneConfederate":6,"DonneTicinesi":1,"DonneStraniere":0},{"Quartiere":110,"Fascia":"20..64","UominiStranieri":0,"UominiTicinesi":0,"UominiConfederati":0,"UominiAttinenti":0,"DonneAttinenti":0,"DonneConfederate":0,"DonneTicinesi":0,"DonneStraniere":2}]