[{"Comparto":-118,"Abitanti":5},{"Comparto":-117,"Abitanti":49},{"Comparto":-116,"Abitanti":1},{"Comparto":-115,"Abitanti":2},{"Comparto":-114,"Abitanti":30},{"Comparto":-113,"Abitanti":9},{"Comparto":-104,"Abitanti":2},{"Comparto":-100,"Abitanti":14},{"Comparto":1,"Abitanti":123},{"Comparto":2,"Abitanti":99},{"Comparto":3,"Abitanti":442},{"Comparto":4,"Abitanti":483},{"Comparto":5,"Abitanti":1142},{"Comparto":6,"Abitanti":140},{"Comparto":7,"Abitanti":63},{"Comparto":8,"Abitanti":408},{"Comparto":9,"Abitanti":390},{"Comparto":10,"Abitanti":15},{"Comparto":11,"Abitanti":710},{"Comparto":12,"Abitanti":874},{"Comparto":13,"Abitanti":128},{"Comparto":14,"Abitanti":360},{"Comparto":15,"Abitanti":628},{"Comparto":16,"Abitanti":643},{"Comparto":17,"Abitanti":1048},{"Comparto":18,"Abitanti":864},{"Comparto":19,"Abitanti":459},{"Comparto":20,"Abitanti":467},{"Comparto":21,"Abitanti":8},{"Comparto":22,"Abitanti":184},{"Comparto":24,"Abitanti":500},{"Comparto":25,"Abitanti":317},{"Comparto":26,"Abitanti":365},{"Comparto":27,"Abitanti":396},{"Comparto":28,"Abitanti":171},{"Comparto":29,"Abitanti":45},{"Comparto":30,"Abitanti":2},{"Comparto":31,"Abitanti":155},{"Comparto":32,"Abitanti":156},{"Comparto":33,"Abitanti":486},{"Comparto":34,"Abitanti":457},{"Comparto":35,"Abitanti":416},{"Comparto":36,"Abitanti":138},{"Comparto":37,"Abitanti":183},{"Comparto":38,"Abitanti":233},{"Comparto":39,"Abitanti":469},{"Comparto":40,"Abitanti":246},{"Comparto":41,"Abitanti":430},{"Comparto":43,"Abitanti":953},{"Comparto":44,"Abitanti":344},{"Comparto":45,"Abitanti":59},{"Comparto":46,"Abitanti":689},{"Comparto":47,"Abitanti":441},{"Comparto":48,"Abitanti":573},{"Comparto":49,"Abitanti":461},{"Comparto":50,"Abitanti":619},{"Comparto":51,"Abitanti":435},{"Comparto":52,"Abitanti":435},{"Comparto":53,"Abitanti":650},{"Comparto":54,"Abitanti":828},{"Comparto":55,"Abitanti":208},{"Comparto":56,"Abitanti":186},{"Comparto":57,"Abitanti":75},{"Comparto":58,"Abitanti":122},{"Comparto":59,"Abitanti":769},{"Comparto":60,"Abitanti":598},{"Comparto":61,"Abitanti":271},{"Comparto":64,"Abitanti":221},{"Comparto":65,"Abitanti":46},{"Comparto":66,"Abitanti":1036},{"Comparto":67,"Abitanti":1012},{"Comparto":68,"Abitanti":1108},{"Comparto":69,"Abitanti":535},{"Comparto":70,"Abitanti":123},{"Comparto":71,"Abitanti":42},{"Comparto":72,"Abitanti":694},{"Comparto":73,"Abitanti":343},{"Comparto":74,"Abitanti":383},{"Comparto":75,"Abitanti":489},{"Comparto":76,"Abitanti":316},{"Comparto":77,"Abitanti":168},{"Comparto":78,"Abitanti":81},{"Comparto":79,"Abitanti":185},{"Comparto":80,"Abitanti":368},{"Comparto":81,"Abitanti":56},{"Comparto":82,"Abitanti":16},{"Comparto":83,"Abitanti":40},{"Comparto":84,"Abitanti":84},{"Comparto":85,"Abitanti":25},{"Comparto":86,"Abitanti":190},{"Comparto":87,"Abitanti":19},{"Comparto":88,"Abitanti":33},{"Comparto":89,"Abitanti":82},{"Comparto":90,"Abitanti":5},{"Comparto":91,"Abitanti":66},{"Comparto":93,"Abitanti":2},{"Comparto":94,"Abitanti":82},{"Comparto":95,"Abitanti":376},{"Comparto":96,"Abitanti":101},{"Comparto":97,"Abitanti":21},{"Comparto":98,"Abitanti":102},{"Comparto":99,"Abitanti":457},{"Comparto":100,"Abitanti":658},{"Comparto":101,"Abitanti":590},{"Comparto":102,"Abitanti":324},{"Comparto":103,"Abitanti":131},{"Comparto":104,"Abitanti":107},{"Comparto":105,"Abitanti":403},{"Comparto":106,"Abitanti":87},{"Comparto":108,"Abitanti":166},{"Comparto":109,"Abitanti":7},{"Comparto":110,"Abitanti":156},{"Comparto":111,"Abitanti":103},{"Comparto":112,"Abitanti":21},{"Comparto":113,"Abitanti":104},{"Comparto":114,"Abitanti":123},{"Comparto":115,"Abitanti":297},{"Comparto":116,"Abitanti":165},{"Comparto":117,"Abitanti":196},{"Comparto":118,"Abitanti":201},{"Comparto":119,"Abitanti":17},{"Comparto":120,"Abitanti":120},{"Comparto":121,"Abitanti":117},{"Comparto":122,"Abitanti":130},{"Comparto":123,"Abitanti":111},{"Comparto":124,"Abitanti":12},{"Comparto":125,"Abitanti":110},{"Comparto":127,"Abitanti":72},{"Comparto":128,"Abitanti":235},{"Comparto":129,"Abitanti":252},{"Comparto":131,"Abitanti":408},{"Comparto":132,"Abitanti":214},{"Comparto":133,"Abitanti":96},{"Comparto":134,"Abitanti":229},{"Comparto":135,"Abitanti":84},{"Comparto":136,"Abitanti":54},{"Comparto":137,"Abitanti":94},{"Comparto":138,"Abitanti":11},{"Comparto":139,"Abitanti":36},{"Comparto":140,"Abitanti":79},{"Comparto":141,"Abitanti":24},{"Comparto":142,"Abitanti":138},{"Comparto":143,"Abitanti":2},{"Comparto":144,"Abitanti":203},{"Comparto":145,"Abitanti":52},{"Comparto":146,"Abitanti":61},{"Comparto":147,"Abitanti":18},{"Comparto":148,"Abitanti":45},{"Comparto":149,"Abitanti":21},{"Comparto":150,"Abitanti":7},{"Comparto":151,"Abitanti":96},{"Comparto":152,"Abitanti":206},{"Comparto":153,"Abitanti":34},{"Comparto":154,"Abitanti":159},{"Comparto":156,"Abitanti":2},{"Comparto":157,"Abitanti":232},{"Comparto":158,"Abitanti":52},{"Comparto":160,"Abitanti":94},{"Comparto":161,"Abitanti":59},{"Comparto":163,"Abitanti":118},{"Comparto":164,"Abitanti":217},{"Comparto":165,"Abitanti":617},{"Comparto":166,"Abitanti":141},{"Comparto":167,"Abitanti":1},{"Comparto":168,"Abitanti":8},{"Comparto":169,"Abitanti":680},{"Comparto":170,"Abitanti":618},{"Comparto":171,"Abitanti":807},{"Comparto":172,"Abitanti":633},{"Comparto":173,"Abitanti":194},{"Comparto":174,"Abitanti":293},{"Comparto":175,"Abitanti":1611},{"Comparto":176,"Abitanti":917},{"Comparto":177,"Abitanti":750},{"Comparto":178,"Abitanti":124},{"Comparto":179,"Abitanti":85},{"Comparto":180,"Abitanti":166},{"Comparto":181,"Abitanti":68},{"Comparto":182,"Abitanti":651},{"Comparto":183,"Abitanti":669},{"Comparto":184,"Abitanti":707},{"Comparto":185,"Abitanti":186},{"Comparto":186,"Abitanti":243},{"Comparto":187,"Abitanti":162},{"Comparto":192,"Abitanti":22},{"Comparto":195,"Abitanti":297},{"Comparto":196,"Abitanti":790},{"Comparto":197,"Abitanti":687},{"Comparto":198,"Abitanti":736},{"Comparto":199,"Abitanti":80},{"Comparto":200,"Abitanti":315},{"Comparto":201,"Abitanti":232},{"Comparto":202,"Abitanti":196},{"Comparto":203,"Abitanti":55},{"Comparto":204,"Abitanti":436},{"Comparto":205,"Abitanti":778},{"Comparto":206,"Abitanti":573},{"Comparto":207,"Abitanti":1277},{"Comparto":208,"Abitanti":1058},{"Comparto":209,"Abitanti":77},{"Comparto":210,"Abitanti":110},{"Comparto":211,"Abitanti":251},{"Comparto":212,"Abitanti":90},{"Comparto":213,"Abitanti":137},{"Comparto":214,"Abitanti":24},{"Comparto":215,"Abitanti":11},{"Comparto":216,"Abitanti":11},{"Comparto":217,"Abitanti":40},{"Comparto":218,"Abitanti":170},{"Comparto":219,"Abitanti":46},{"Comparto":220,"Abitanti":137},{"Comparto":221,"Abitanti":60},{"Comparto":222,"Abitanti":515},{"Comparto":223,"Abitanti":106},{"Comparto":224,"Abitanti":150},{"Comparto":225,"Abitanti":5},{"Comparto":226,"Abitanti":103},{"Comparto":228,"Abitanti":168},{"Comparto":229,"Abitanti":321},{"Comparto":230,"Abitanti":4},{"Comparto":231,"Abitanti":134},{"Comparto":232,"Abitanti":77},{"Comparto":233,"Abitanti":83},{"Comparto":234,"Abitanti":568},{"Comparto":235,"Abitanti":188},{"Comparto":236,"Abitanti":2391},{"Comparto":237,"Abitanti":876},{"Comparto":238,"Abitanti":57},{"Comparto":239,"Abitanti":177},{"Comparto":240,"Abitanti":1906},{"Comparto":241,"Abitanti":806}]