[{"Quartiere":1,"Cittadinanza":"Attinente","measure":3},{"Quartiere":2,"Cittadinanza":"Attinente","measure":4},{"Quartiere":3,"Cittadinanza":"Attinente","measure":2},{"Quartiere":4,"Cittadinanza":"Attinente","measure":7},{"Quartiere":5,"Cittadinanza":"Attinente","measure":2},{"Quartiere":6,"Cittadinanza":"Attinente","measure":7},{"Quartiere":7,"Cittadinanza":"Attinente","measure":2},{"Quartiere":9,"Cittadinanza":"Attinente","measure":3},{"Quartiere":11,"Cittadinanza":"Attinente","measure":4},{"Quartiere":12,"Cittadinanza":"Attinente","measure":5},{"Quartiere":15,"Cittadinanza":"Attinente","measure":3},{"Quartiere":16,"Cittadinanza":"Attinente","measure":3},{"Quartiere":17,"Cittadinanza":"Attinente","measure":2},{"Quartiere":18,"Cittadinanza":"Attinente","measure":2},{"Quartiere":19,"Cittadinanza":"Attinente","measure":2},{"Quartiere":21,"Cittadinanza":"Attinente","measure":1},{"Quartiere":24,"Cittadinanza":"Attinente","measure":5},{"Quartiere":25,"Cittadinanza":"Attinente","measure":2},{"Quartiere":26,"Cittadinanza":"Attinente","measure":14},{"Quartiere":106,"Cittadinanza":"Attinente","measure":1},{"Quartiere":1,"Cittadinanza":"Ticinese","measure":3},{"Quartiere":2,"Cittadinanza":"Ticinese","measure":11},{"Quartiere":3,"Cittadinanza":"Ticinese","measure":5},{"Quartiere":4,"Cittadinanza":"Ticinese","measure":6},{"Quartiere":5,"Cittadinanza":"Ticinese","measure":9},{"Quartiere":6,"Cittadinanza":"Ticinese","measure":14},{"Quartiere":7,"Cittadinanza":"Ticinese","measure":25},{"Quartiere":9,"Cittadinanza":"Ticinese","measure":6},{"Quartiere":10,"Cittadinanza":"Ticinese","measure":3},{"Quartiere":11,"Cittadinanza":"Ticinese","measure":9},{"Quartiere":12,"Cittadinanza":"Ticinese","measure":10},{"Quartiere":13,"Cittadinanza":"Ticinese","measure":1},{"Quartiere":14,"Cittadinanza":"Ticinese","measure":3},{"Quartiere":15,"Cittadinanza":"Ticinese","measure":11},{"Quartiere":16,"Cittadinanza":"Ticinese","measure":9},{"Quartiere":17,"Cittadinanza":"Ticinese","measure":5},{"Quartiere":18,"Cittadinanza":"Ticinese","measure":1},{"Quartiere":20,"Cittadinanza":"Ticinese","measure":2},{"Quartiere":21,"Cittadinanza":"Ticinese","measure":2},{"Quartiere":22,"Cittadinanza":"Ticinese","measure":1},{"Quartiere":24,"Cittadinanza":"Ticinese","measure":3},{"Quartiere":26,"Cittadinanza":"Ticinese","measure":6},{"Quartiere":106,"Cittadinanza":"Ticinese","measure":6},{"Quartiere":1,"Cittadinanza":"Confederato","measure":118},{"Quartiere":2,"Cittadinanza":"Confederato","measure":67},{"Quartiere":3,"Cittadinanza":"Confederato","measure":32},{"Quartiere":4,"Cittadinanza":"Confederato","measure":59},{"Quartiere":5,"Cittadinanza":"Confederato","measure":39},{"Quartiere":6,"Cittadinanza":"Confederato","measure":174},{"Quartiere":7,"Cittadinanza":"Confederato","measure":64},{"Quartiere":8,"Cittadinanza":"Confederato","measure":5},{"Quartiere":9,"Cittadinanza":"Confederato","measure":15},{"Quartiere":10,"Cittadinanza":"Confederato","measure":41},{"Quartiere":11,"Cittadinanza":"Confederato","measure":60},{"Quartiere":12,"Cittadinanza":"Confederato","measure":79},{"Quartiere":13,"Cittadinanza":"Confederato","measure":3},{"Quartiere":14,"Cittadinanza":"Confederato","measure":26},{"Quartiere":15,"Cittadinanza":"Confederato","measure":145},{"Quartiere":16,"Cittadinanza":"Confederato","measure":86},{"Quartiere":17,"Cittadinanza":"Confederato","measure":99},{"Quartiere":18,"Cittadinanza":"Confederato","measure":5},{"Quartiere":19,"Cittadinanza":"Confederato","measure":2},{"Quartiere":20,"Cittadinanza":"Confederato","measure":1},{"Quartiere":21,"Cittadinanza":"Confederato","measure":40},{"Quartiere":22,"Cittadinanza":"Confederato","measure":16},{"Quartiere":24,"Cittadinanza":"Confederato","measure":7},{"Quartiere":25,"Cittadinanza":"Confederato","measure":6},{"Quartiere":26,"Cittadinanza":"Confederato","measure":40},{"Quartiere":106,"Cittadinanza":"Confederato","measure":27},{"Quartiere":1,"Cittadinanza":"Straniero","measure":66},{"Quartiere":2,"Cittadinanza":"Straniero","measure":53},{"Quartiere":3,"Cittadinanza":"Straniero","measure":3},{"Quartiere":4,"Cittadinanza":"Straniero","measure":43},{"Quartiere":5,"Cittadinanza":"Straniero","measure":87},{"Quartiere":6,"Cittadinanza":"Straniero","measure":249},{"Quartiere":7,"Cittadinanza":"Straniero","measure":140},{"Quartiere":8,"Cittadinanza":"Straniero","measure":1},{"Quartiere":9,"Cittadinanza":"Straniero","measure":6},{"Quartiere":10,"Cittadinanza":"Straniero","measure":7},{"Quartiere":11,"Cittadinanza":"Straniero","measure":158},{"Quartiere":12,"Cittadinanza":"Straniero","measure":81},{"Quartiere":13,"Cittadinanza":"Straniero","measure":2},{"Quartiere":14,"Cittadinanza":"Straniero","measure":23},{"Quartiere":15,"Cittadinanza":"Straniero","measure":37},{"Quartiere":16,"Cittadinanza":"Straniero","measure":58},{"Quartiere":17,"Cittadinanza":"Straniero","measure":74},{"Quartiere":18,"Cittadinanza":"Straniero","measure":4},{"Quartiere":19,"Cittadinanza":"Straniero","measure":2},{"Quartiere":21,"Cittadinanza":"Straniero","measure":15},{"Quartiere":22,"Cittadinanza":"Straniero","measure":9},{"Quartiere":23,"Cittadinanza":"Straniero","measure":1},{"Quartiere":25,"Cittadinanza":"Straniero","measure":2},{"Quartiere":26,"Cittadinanza":"Straniero","measure":1},{"Quartiere":106,"Cittadinanza":"Straniero","measure":18}]