[{"Eta":"90..99         ","Uomini":2,"EtaUomini":182,"Donne":2,"EtaDonne":190},{"Eta":"80..89         ","Uomini":10,"EtaUomini":832,"Donne":12,"EtaDonne":1021},{"Eta":"70..79         ","Uomini":34,"EtaUomini":2493,"Donne":32,"EtaDonne":2397},{"Eta":"60..69         ","Uomini":52,"EtaUomini":3339,"Donne":42,"EtaDonne":2687},{"Eta":"50..59         ","Uomini":46,"EtaUomini":2508,"Donne":42,"EtaDonne":2295},{"Eta":"40..49         ","Uomini":112,"EtaUomini":4905,"Donne":72,"EtaDonne":3166},{"Eta":"30..39         ","Uomini":183,"EtaUomini":6315,"Donne":154,"EtaDonne":5235},{"Eta":"20..29         ","Uomini":238,"EtaUomini":5885,"Donne":271,"EtaDonne":6491},{"Eta":"10..19         ","Uomini":76,"EtaUomini":1204,"Donne":79,"EtaDonne":1349},{"Eta":"0..9           ","Uomini":30,"EtaUomini":121,"Donne":44,"EtaDonne":173},{"Eta":"Sconosciuto    ","Uomini":0,"EtaUomini":0,"Donne":1,"EtaDonne":-1}]