[{"Fascia":"65..","UominiStranieri":2267,"UominiTicinesi":1433,"UominiConfederati":1282,"UominiAttinenti":1647,"DonneAttinenti":2519,"DonneConfederate":1958,"DonneTicinesi":2309,"DonneStraniere":2337},{"Fascia":"20..64","UominiStranieri":9354,"UominiTicinesi":3918,"UominiConfederati":2651,"UominiAttinenti":4230,"DonneAttinenti":4789,"DonneConfederate":3024,"DonneTicinesi":4244,"DonneStraniere":8437},{"Fascia":"0..19","UominiStranieri":1834,"UominiTicinesi":1318,"UominiConfederati":867,"UominiAttinenti":1576,"DonneAttinenti":1441,"DonneConfederate":850,"DonneTicinesi":1264,"DonneStraniere":1687}]