[{"Eta":"90..99         ","Uomini":1,"EtaUomini":91,"Donne":5,"EtaDonne":468},{"Eta":"80..89         ","Uomini":13,"EtaUomini":1087,"Donne":13,"EtaDonne":1091},{"Eta":"70..79         ","Uomini":36,"EtaUomini":2666,"Donne":25,"EtaDonne":1837},{"Eta":"60..69         ","Uomini":55,"EtaUomini":3556,"Donne":40,"EtaDonne":2611},{"Eta":"50..59         ","Uomini":86,"EtaUomini":4687,"Donne":69,"EtaDonne":3757},{"Eta":"40..49         ","Uomini":129,"EtaUomini":5773,"Donne":85,"EtaDonne":3731},{"Eta":"30..39         ","Uomini":167,"EtaUomini":5643,"Donne":160,"EtaDonne":5458},{"Eta":"20..29         ","Uomini":215,"EtaUomini":5378,"Donne":294,"EtaDonne":7230},{"Eta":"10..19         ","Uomini":37,"EtaUomini":600,"Donne":40,"EtaDonne":656},{"Eta":"0..9           ","Uomini":46,"EtaUomini":173,"Donne":43,"EtaDonne":129},{"Eta":"Sconosciuto    ","Uomini":1,"EtaUomini":-1,"Donne":1,"EtaDonne":-1}]