[{"Fascia":"65..","UominiStranieri":2335,"UominiTicinesi":1478,"UominiConfederati":1360,"UominiAttinenti":1743,"DonneAttinenti":2550,"DonneConfederate":2038,"DonneTicinesi":2321,"DonneStraniere":2434},{"Fascia":"20..64","UominiStranieri":9586,"UominiTicinesi":3962,"UominiConfederati":2638,"UominiAttinenti":4340,"DonneAttinenti":4736,"DonneConfederate":2874,"DonneTicinesi":4149,"DonneStraniere":8725},{"Fascia":"0..19","UominiStranieri":1993,"UominiTicinesi":1288,"UominiConfederati":811,"UominiAttinenti":1539,"DonneAttinenti":1425,"DonneConfederate":791,"DonneTicinesi":1224,"DonneStraniere":1879}]