[{"Eta":"100..109       ","Uomini":2,"EtaUomini":204,"Donne":3,"EtaDonne":306},{"Eta":"90..99         ","Uomini":14,"EtaUomini":1320,"Donne":15,"EtaDonne":1420},{"Eta":"80..89         ","Uomini":36,"EtaUomini":3017,"Donne":39,"EtaDonne":3305},{"Eta":"70..79         ","Uomini":67,"EtaUomini":4969,"Donne":48,"EtaDonne":3562},{"Eta":"60..69         ","Uomini":120,"EtaUomini":7685,"Donne":100,"EtaDonne":6400},{"Eta":"50..59         ","Uomini":186,"EtaUomini":10108,"Donne":145,"EtaDonne":7846},{"Eta":"40..49         ","Uomini":425,"EtaUomini":18702,"Donne":354,"EtaDonne":15520},{"Eta":"30..39         ","Uomini":508,"EtaUomini":17415,"Donne":524,"EtaDonne":17945},{"Eta":"20..29         ","Uomini":392,"EtaUomini":9819,"Donne":503,"EtaDonne":12617},{"Eta":"10..19         ","Uomini":144,"EtaUomini":2172,"Donne":143,"EtaDonne":2195},{"Eta":"0..9           ","Uomini":155,"EtaUomini":685,"Donne":153,"EtaDonne":695},{"Eta":"Sconosciuto    ","Uomini":1,"EtaUomini":-1,"Donne":1,"EtaDonne":-1}]